odoo_commands/__init__.py
odoo_commands/app.py
odoo_commands/config.py
odoo_commands/createdb.py
odoo_commands/data_generator.py
odoo_commands/database_mock.py
odoo_commands/generate_pot.py
odoo_commands/module.py
odoo_commands/module_set.py
odoo_commands/nighly.py
odoo_commands/odoo_translate.py
odoo_commands/project.py
odoo_commands/test_env.py
odoo_commands/test_property.py
odoo_commands/test_registry.py
odoo_commands/test_xml_parsing.py
odoo_commands/utils.py
odoo_commands-0.7.dist-info/LICENSE
odoo_commands-0.7.dist-info/METADATA
odoo_commands-0.7.dist-info/WHEEL
odoo_commands-0.7.dist-info/entry_points.txt
odoo_commands-0.7.dist-info/RECORD
